flirpy/__init__.py
flirpy/bin/exiftool
flirpy/bin/exiftool.exe
flirpy/bin/find_cameras.exe
flirpy/bin/arg_files/exif2iptc.args
flirpy/bin/arg_files/exif2xmp.args
flirpy/bin/arg_files/gps2xmp.args
flirpy/bin/arg_files/iptc2exif.args
flirpy/bin/arg_files/iptc2xmp.args
flirpy/bin/arg_files/iptcCore.args
flirpy/bin/arg_files/pdf2xmp.args
flirpy/bin/arg_files/xmp2exif.args
flirpy/bin/arg_files/xmp2gps.args
flirpy/bin/arg_files/xmp2iptc.args
flirpy/bin/arg_files/xmp2pdf.args
flirpy/bin/config_files/age.config
flirpy/bin/config_files/bibble.config
flirpy/bin/config_files/convert_regions.config
flirpy/bin/config_files/dji.config
flirpy/bin/config_files/example.config
flirpy/bin/config_files/fotoware.config
flirpy/bin/config_files/gps2utm.config
flirpy/bin/config_files/photoshop_paths.config
flirpy/bin/config_files/picasa_faces.config
flirpy/bin/config_files/time_zone.config
flirpy/bin/fmt_files/gpx.fmt
flirpy/bin/fmt_files/gpx_wpt.fmt
flirpy/bin/fmt_files/kml.fmt
flirpy/bin/lib/File/RandomAccess.pm
flirpy/bin/lib/File/RandomAccess.pod
flirpy/bin/lib/Image/ExifTool.pm
flirpy/bin/lib/Image/ExifTool.pod
flirpy/bin/lib/Image/ExifTool/AES.pm
flirpy/bin/lib/Image/ExifTool/AFCP.pm
flirpy/bin/lib/Image/ExifTool/AIFF.pm
flirpy/bin/lib/Image/ExifTool/APE.pm
flirpy/bin/lib/Image/ExifTool/APP12.pm
flirpy/bin/lib/Image/ExifTool/ASF.pm
flirpy/bin/lib/Image/ExifTool/Apple.pm
flirpy/bin/lib/Image/ExifTool/Audible.pm
flirpy/bin/lib/Image/ExifTool/BMP.pm
flirpy/bin/lib/Image/ExifTool/BPG.pm
flirpy/bin/lib/Image/ExifTool/BZZ.pm
flirpy/bin/lib/Image/ExifTool/BigTIFF.pm
flirpy/bin/lib/Image/ExifTool/BuildTagLookup.pm
flirpy/bin/lib/Image/ExifTool/Canon.pm
flirpy/bin/lib/Image/ExifTool/CanonCustom.pm
flirpy/bin/lib/Image/ExifTool/CanonRaw.pm
flirpy/bin/lib/Image/ExifTool/CanonVRD.pm
flirpy/bin/lib/Image/ExifTool/CaptureOne.pm
flirpy/bin/lib/Image/ExifTool/Casio.pm
flirpy/bin/lib/Image/ExifTool/Charset.pm
flirpy/bin/lib/Image/ExifTool/DICOM.pm
flirpy/bin/lib/Image/ExifTool/DJI.pm
flirpy-0.3.0.dist-info/LICENSE.md
flirpy-0.3.0.dist-info/METADATA
flirpy-0.3.0.dist-info/WHEEL
flirpy-0.3.0.dist-info/top_level.txt
flirpy-0.3.0.dist-info/RECORD
