Metadata-Version: 2.1
Name: flirpy
Version: 0.3.0
Summary: UNKNOWN
Home-page: UNKNOWN
Author: Josh Veitch-Michaelis
Author-email: j.veitchmichaelis@gmail.com
License: MIT
Platform: UNKNOWN
